sensu/__init__.py
sensu/cli.py
sensu_cli-0.1.0.dist-info/DESCRIPTION.rst
sensu_cli-0.1.0.dist-info/METADATA
sensu_cli-0.1.0.dist-info/RECORD
sensu_cli-0.1.0.dist-info/WHEEL
sensu_cli-0.1.0.dist-info/entry_points.txt
sensu_cli-0.1.0.dist-info/metadata.json
sensu_cli-0.1.0.dist-info/top_level.txt
