Metadata-Version: 2.0
Name: sensu-cli
Version: 0.1.0
Summary: A convenient CLI around some of the Sensu ReST API
Home-page: https://github.com/dhutty/sensu-cli
Author: Duncan Hutty
Author-email: dhutty@allgoodbits.org
License: BSD
Download-URL: https://github.com/dhutty/sensu-cli/tarball/0.1.0
Platform: UNKNOWN
Classifier: Development Status :: 3 - Alpha
Classifier: Environment :: Console
Classifier: Operating System :: OS Independent
Classifier: Topic :: System :: Monitoring
Classifier: Intended Audience :: System Administrators
Classifier: Programming Language :: Python :: 2
Classifier: Programming Language :: Python :: 3
Requires-Dist: click
Requires-Dist: requests
Requires-Dist: pysensu-ng
